pants_backend_k8s/__init__.py
pants_backend_k8s/goals/__init__.py
pants_backend_k8s/goals/run.py
pants_backend_k8s/register.py
pants_backend_k8s/subsystem.py
pants_backend_k8s/target_generators.py
pants_backend_k8s/target_types.py
pants_backend_k8s/util/kubeconfig.py
pants_backend_k8s-0.5.0.dist-info/WHEEL
pants_backend_k8s-0.5.0.dist-info/METADATA
pants_backend_k8s-0.5.0.dist-info/licenses/LICENSE-MIT.txt
pants_backend_k8s-0.5.0.dist-info/RECORD
