Metadata-Version: 2.1
Name: pants_backend_k8s
Version: 0.5.0
Summary: A Kubernetes plugin for the Pants build system
Keywords: pantsbuild,pants,backend,kubernetes
Author-email: Tom Solberg <me@sbg.dev>
Classifier: Development Status :: 4 - Beta
Classifier: Programming Language :: Python
Classifier: Topic :: Software Development :: Build Tools
Project-URL: Changelog, https://github.com/tgolsson/pants-backends/tree/main/pants-plugins/k8s/CHANGELOG.md
Project-URL: Code, https://github.com/tgolsson/pants-backends/tree/main/pants-plugins/k8s
Project-URL: Repository, https://github.com/tgolsson/pants-backends
